fuzzy/__init__.py
fuzzy/collections.py
fuzzy/_src/__init__.py
fuzzy/_src/fuzzy_frozen_dict.py
fuzzy/_src/fuzzy_frozen_set.py
easy_fuzzy-0.0.2.dist-info/LICENSE
easy_fuzzy-0.0.2.dist-info/METADATA
easy_fuzzy-0.0.2.dist-info/WHEEL
easy_fuzzy-0.0.2.dist-info/top_level.txt
easy_fuzzy-0.0.2.dist-info/RECORD
